wordzs/__init__.py
Wordzs-0.0.2.dist-info/LICENCE.txt
Wordzs-0.0.2.dist-info/METADATA
Wordzs-0.0.2.dist-info/WHEEL
Wordzs-0.0.2.dist-info/top_level.txt
Wordzs-0.0.2.dist-info/RECORD
